PyEmotion/__init__.py
PyEmotion/main.py
PyEmotion/networks.py
PyEmotion/model/main_model.pkl
PyEmotion-1.0.0.dist-info/LICENSE.txt
PyEmotion-1.0.0.dist-info/METADATA
PyEmotion-1.0.0.dist-info/WHEEL
PyEmotion-1.0.0.dist-info/dependency_links.txt
PyEmotion-1.0.0.dist-info/top_level.txt
PyEmotion-1.0.0.dist-info/RECORD
