Metadata-Version: 2.1
Name: PyEmotion
Version: 1.0.0
Summary: A PyTorch library for detecting facial emotions
Home-page: UNKNOWN
Author: Karthick Nagarajan
Author-email: karthick965938@gmail.com
License: MIT
Keywords: image data datascience emotion PyEmotion expression ML ml machinelearning AI ai
Platform: UNKNOWN
Classifier: Programming Language :: Python :: 3
Classifier: Programming Language :: Python :: 3.6
Classifier: Programming Language :: Python :: 3.7
Requires-Dist: opencv-python
Requires-Dist: Pillow
Requires-Dist: art
Requires-Dist: termcolor
Requires-Dist: progress
Requires-Dist: pytest
Requires-Dist: facenet-pytorch
Requires-Dist: numpy
